mylib022/__init__.py
mylib022-0.1.dist-info/LICENSE.txt
mylib022-0.1.dist-info/METADATA
mylib022-0.1.dist-info/WHEEL
mylib022-0.1.dist-info/top_level.txt
mylib022-0.1.dist-info/RECORD
